Metadata-Version: 2.1
Name: PI-webscrapping
Version: 1.0.0
Summary: This package performs a webscrapping using RPA techniques
Home-page: https://github.com/luizschmall/PI_webscrapping
Author: Luiz Otávio Schmall dos Santos
Author-email: luizschmall@gmail.com
License: MIT
Platform: UNKNOWN
